gorgonzola/__init__.py
gorgonzola/aws_boto_session.py
gorgonzola/aws_dynamodb_table.py
gorgonzola/aws_iam_alias.py
gorgonzola/aws_iam_idp.py
gorgonzola/aws_iam_roles.py
gorgonzola/aws_lambda_function.py
gorgonzola/aws_organizations.py
gorgonzola/aws_s3_buckets.py
gorgonzola/aws_ssm_global_parameters.py
gorgonzola/aws_sts_credentials.py
gorgonzola-0.2.0.dist-info/LICENSE
gorgonzola-0.2.0.dist-info/METADATA
gorgonzola-0.2.0.dist-info/WHEEL
gorgonzola-0.2.0.dist-info/top_level.txt
gorgonzola-0.2.0.dist-info/RECORD
