Metadata-Version: 2.1
Name: gorgonzola
Version: 0.2.0
Summary: AWS Boto3 helper functions for multi-account control
Home-page: https://github.com/shibboleth66/gorgonzola
Author: Ben Gallagher
Author-email: shibboleth@me.com
License: UNKNOWN
Platform: UNKNOWN
Classifier: Programming Language :: Python :: 3
Classifier: License :: OSI Approved :: MIT License
Classifier: Operating System :: OS Independent
Requires-Dist: boto3 (>=1.9.96)
